README.md
setup.py
arboreal/__init__.py
arboreal/dtypes.py
arboreal.egg-info/PKG-INFO
arboreal.egg-info/SOURCES.txt
arboreal.egg-info/dependency_links.txt
arboreal.egg-info/not-zip-safe
arboreal.egg-info/requires.txt
arboreal.egg-info/top_level.txt
arboreal/impurity/__init__.py
arboreal/impurity/impurity.py
arboreal/split/__init__.py
arboreal/split/split.py
arboreal/split/splitters.py
arboreal/tree/__init__.py
arboreal/tree/tree.py