Metadata-Version: 1.0
Name: arboreal
Version: 0.1.2
Summary: Python package to modularly create decision trees
Home-page: http://github.com/ankur-gupta/arboreal
Author: Ankur Gupta
Author-email: ankur@perfectlyrandom.org
License: MIT
Keywords: decision tree modular missing value categorical feature
Platform: UNKNOWN
